pylogininglogs/__init__.py
pylogininglogs-0.1.3.dist-info/licenses/LICENSE
pylogininglogs-0.1.3.dist-info/METADATA
pylogininglogs-0.1.3.dist-info/WHEEL
pylogininglogs-0.1.3.dist-info/top_level.txt
pylogininglogs-0.1.3.dist-info/RECORD
