Metadata-Version: 2.4
Name: pylogininglogs
Version: 0.1.3
Summary: A custom logging library wrapper with convenient defaults
Home-page: https://github.com/yourusername/pylogininglogs
Author: Your Name
Author-email: Your Name <your.email@example.com>
Classifier: Development Status :: 3 - Alpha
Classifier: Intended Audience :: Developers
Classifier: Topic :: Software Development :: Libraries :: Python Modules
Classifier: Topic :: System :: Logging
Classifier: License :: OSI Approved :: MIT License
Classifier: Programming Language :: Python :: 3
Requires-Python: >=3.7
License-File: LICENSE
Provides-Extra: dev
Requires-Dist: pytest>=7.0; extra == "dev"
Requires-Dist: black; extra == "dev"
Requires-Dist: flake8; extra == "dev"
Dynamic: author
Dynamic: home-page
Dynamic: license-file
Dynamic: requires-python
